media_app/__init__.py
media_app/admin.py
media_app/apps.py
media_app/decorators.py
media_app/mixins.py
media_app/models.py
media_app/serializers.py
media_app/tests.py
media_app/utils.py
media_app/views.py
media_app/migrations/0001_initial.py
media_app/migrations/__init__.py
django_media_app-0.5.2.dist-info/LICENSE
django_media_app-0.5.2.dist-info/METADATA
django_media_app-0.5.2.dist-info/WHEEL
django_media_app-0.5.2.dist-info/top_level.txt
django_media_app-0.5.2.dist-info/RECORD
